azure/mgmt/devopsinfrastructure/__init__.py
azure/mgmt/devopsinfrastructure/_client.py
azure/mgmt/devopsinfrastructure/_configuration.py
azure/mgmt/devopsinfrastructure/_model_base.py
azure/mgmt/devopsinfrastructure/_patch.py
azure/mgmt/devopsinfrastructure/_serialization.py
azure/mgmt/devopsinfrastructure/_version.py
azure/mgmt/devopsinfrastructure/py.typed
azure/mgmt/devopsinfrastructure/aio/__init__.py
azure/mgmt/devopsinfrastructure/aio/_client.py
azure/mgmt/devopsinfrastructure/aio/_configuration.py
azure/mgmt/devopsinfrastructure/aio/_patch.py
azure/mgmt/devopsinfrastructure/aio/operations/__init__.py
azure/mgmt/devopsinfrastructure/aio/operations/_operations.py
azure/mgmt/devopsinfrastructure/aio/operations/_patch.py
azure/mgmt/devopsinfrastructure/models/__init__.py
azure/mgmt/devopsinfrastructure/models/_enums.py
azure/mgmt/devopsinfrastructure/models/_models.py
azure/mgmt/devopsinfrastructure/models/_patch.py
azure/mgmt/devopsinfrastructure/operations/__init__.py
azure/mgmt/devopsinfrastructure/operations/_operations.py
azure/mgmt/devopsinfrastructure/operations/_patch.py
azure_mgmt_devopsinfrastructure-1.0.0.dist-info/LICENSE
azure_mgmt_devopsinfrastructure-1.0.0.dist-info/METADATA
azure_mgmt_devopsinfrastructure-1.0.0.dist-info/WHEEL
azure_mgmt_devopsinfrastructure-1.0.0.dist-info/top_level.txt
azure_mgmt_devopsinfrastructure-1.0.0.dist-info/RECORD
